minitap/mcp/__init__.py
minitap/mcp/core/agents/compare_screenshots/agent.py
minitap/mcp/core/agents/compare_screenshots/eval/prompts/prompt_1.md
minitap/mcp/core/agents/compare_screenshots/eval/scenario_1_add_cartoon_img_and_move_button/actual.png
minitap/mcp/core/agents/compare_screenshots/eval/scenario_1_add_cartoon_img_and_move_button/figma.png
minitap/mcp/core/agents/compare_screenshots/eval/scenario_1_add_cartoon_img_and_move_button/human_feedback.txt
minitap/mcp/core/agents/compare_screenshots/eval/scenario_1_add_cartoon_img_and_move_button/prompt_1/model_params.json
minitap/mcp/core/agents/compare_screenshots/eval/scenario_1_add_cartoon_img_and_move_button/prompt_1/output.md
minitap/mcp/core/agents/compare_screenshots/prompt.md
minitap/mcp/core/cloud_apk.py
minitap/mcp/core/config.py
minitap/mcp/core/decorators.py
minitap/mcp/core/device.py
minitap/mcp/core/llm.py
minitap/mcp/core/logging_config.py
minitap/mcp/core/models.py
minitap/mcp/core/sdk_agent.py
minitap/mcp/core/storage.py
minitap/mcp/core/task_runs.py
minitap/mcp/core/utils/figma.py
minitap/mcp/core/utils/images.py
minitap/mcp/main.py
minitap/mcp/server/cloud_mobile.py
minitap/mcp/server/middleware.py
minitap/mcp/server/poller.py
minitap/mcp/server/remote_proxy.py
minitap/mcp/tools/execute_mobile_command.py
minitap/mcp/tools/read_swift_logs.py
minitap/mcp/tools/screen_analyzer.md
minitap/mcp/tools/take_screenshot.py
minitap/mcp/tools/upload_screenshot.py
minitap_mcp-0.9.0.dist-info/WHEEL
minitap_mcp-0.9.0.dist-info/entry_points.txt
minitap_mcp-0.9.0.dist-info/METADATA
minitap_mcp-0.9.0.dist-info/RECORD
