Metadata-Version: 2.3
Name: minitap-mcp
Version: 0.9.0
Summary: Model Context Protocol server for controlling Android & iOS devices with natural language
Author: Pierre-Louis Favreau, Jean-Pierre Lo, Clément Guiguet
Requires-Dist: fastmcp>=2.12.4
Requires-Dist: python-dotenv>=1.1.1
Requires-Dist: pydantic>=2.12.0
Requires-Dist: pydantic-settings>=2.10.1
Requires-Dist: minitap-mobile-use>=3.4.0
Requires-Dist: jinja2>=3.1.6
Requires-Dist: langchain-core>=0.3.75
Requires-Dist: pillow>=11.1.0
Requires-Dist: structlog>=24.4.0
Requires-Dist: aiohttp>=3.9.0
Requires-Dist: httpx>=0.28.1
Requires-Dist: ruff==0.5.3 ; extra == 'dev'
Requires-Dist: pytest==8.4.1 ; extra == 'dev'
Requires-Dist: pytest-cov==5.0.0 ; extra == 'dev'
Requires-Python: >=3.12
Project-URL: Homepage, https://minitap.ai/
Project-URL: Source, https://github.com/minitap-ai/mobile-use
Provides-Extra: dev
